README.txt
setup.cfg
setup.py
collective/__init__.py
collective.jstree.egg-info/PKG-INFO
collective.jstree.egg-info/SOURCES.txt
collective.jstree.egg-info/dependency_links.txt
collective.jstree.egg-info/entry_points.txt
collective.jstree.egg-info/namespace_packages.txt
collective.jstree.egg-info/not-zip-safe
collective.jstree.egg-info/requires.txt
collective.jstree.egg-info/top_level.txt
collective/jstree/__init__.py
collective/jstree/configure.zcml
collective/jstree/jquery.zcml
collective/jstree/jsTree/changelog.txt
collective/jstree/jsTree/reference/index.html
collective/jstree/jsTree/reference/_documentation/1_files.html
collective/jstree/jsTree/reference/_documentation/2_creation.html
collective/jstree/jsTree/reference/_documentation/3_configuration.html
collective/jstree/jsTree/reference/_documentation/4_data.html
collective/jstree/jsTree/reference/_documentation/5_customize.html
collective/jstree/jsTree/reference/_documentation/6_output.html
collective/jstree/jsTree/reference/_documentation/7_api.html
collective/jstree/jsTree/reference/_examples/1_async.php
collective/jstree/jsTree/reference/_examples/1_datasources.html
collective/jstree/jsTree/reference/_examples/1_xml_flat.xml
collective/jstree/jsTree/reference/_examples/2_operations.html
collective/jstree/jsTree/reference/_examples/3_callbacks.html
collective/jstree/jsTree/reference/_examples/4_themes.html
collective/jstree/jsTree/reference/_examples/5_others.html
collective/jstree/jsTree/reference/_examples/7_full.html
collective/jstree/jsTree/reference/_examples/darkness/style.css
collective/jstree/jsTree/reference/_examples/darkness/images/ui-bg_flat_30_cccccc_40x100.png
collective/jstree/jsTree/reference/_examples/darkness/images/ui-bg_flat_50_5c5c5c_40x100.png
collective/jstree/jsTree/reference/_examples/darkness/images/ui-bg_glass_20_555555_1x400.png
collective/jstree/jsTree/reference/_examples/darkness/images/ui-bg_glass_40_0078a3_1x400.png
collective/jstree/jsTree/reference/_examples/darkness/images/ui-bg_glass_40_ffc73d_1x400.png
collective/jstree/jsTree/reference/_examples/darkness/images/ui-bg_gloss-wave_25_333333_500x100.png
collective/jstree/jsTree/reference/_examples/darkness/images/ui-bg_highlight-soft_80_eeeeee_1x100.png
collective/jstree/jsTree/reference/_examples/darkness/images/ui-bg_inset-soft_25_000000_1x100.png
