Metadata-Version: 1.0
Name: collective.jstree
Version: 0.9.7
Summary: jsTree as a zope resource
Home-page: http://svn.plone.org/svn/collective/collective.jstree
Author: Sasha Vincic
Author-email: UNKNOWN
License: GPL
Platform: UNKNOWN
Classifier: Programming Language :: Python
Classifier: Topic :: Software Development :: Libraries :: Python Modules
